napari_trait2d/__init__.py
napari_trait2d/_widget.py
napari_trait2d/common.py
napari_trait2d/detection.py
napari_trait2d/napari.yaml
napari_trait2d/tracking.py
napari_trait2d/workflow.py
napari_trait2d/_tests/__init__.py
napari_trait2d/_tests/test_widget.py
napari_trait2d-0.1.4.dist-info/LICENSE
napari_trait2d-0.1.4.dist-info/METADATA
napari_trait2d-0.1.4.dist-info/WHEEL
napari_trait2d-0.1.4.dist-info/entry_points.txt
napari_trait2d-0.1.4.dist-info/top_level.txt
napari_trait2d-0.1.4.dist-info/RECORD
