Metadata-Version: 2.1
Name: napari-trait2d
Version: 0.1.4
Summary: A napari plugin for TRAIT2D, a software for quantitative analysis of single particle diffusion data
Home-page: https://github.com/jacopoabramo/napari-trait2d
Author: Jacopo Abramo
Author-email: jacopo.abramo@gmail.com
License: BSD-3-Clause
Project-URL: Bug Tracker, https://github.com/jacopoabramo/napari-trait2d/issues
Project-URL: Documentation, https://github.com/jacopoabramo/napari-trait2d#README.md
Project-URL: Source Code, https://github.com/jacopoabramo/napari-trait2d
Project-URL: User Support, https://github.com/jacopoabramo/napari-trait2d/issues
Classifier: Development Status :: 2 - Pre-Alpha
Classifier: Framework :: napari
Classifier: Intended Audience :: Developers
Classifier: License :: OSI Approved :: BSD License
Classifier: Operating System :: OS Independent
Classifier: Programming Language :: Python
Classifier: Programming Language :: Python :: 3
Classifier: Programming Language :: Python :: 3 :: Only
Classifier: Programming Language :: Python :: 3.8
Classifier: Programming Language :: Python :: 3.9
Classifier: Programming Language :: Python :: 3.10
Requires-Python: >=3.8
License-File: LICENSE
Requires-Dist: numpy
Requires-Dist: qtpy
Requires-Dist: napari[pyqt5]
Requires-Dist: dacite
Provides-Extra: testing
Requires-Dist: tox ; extra == 'testing'
Requires-Dist: pytest ; extra == 'testing'
Requires-Dist: pytest-cov ; extra == 'testing'
Requires-Dist: pytest-qt ; extra == 'testing'
